smoke_tests/__init__.py
smoke_tests/test10_audio_integration.py
smoke_tests/test11_realtime_voice_streaming.py
smoke_tests/test12_audio_benchmarks.py
smoke_tests/test13_base_engine_audio_engine_compatibility.py
smoke_tests/test1_audio_types.py
smoke_tests/test2_audio_processor.py
smoke_tests/test3_audio_engine.py
smoke_tests/test4_direct_audio_capture.py
smoke_tests/test5_direct_audio_player.py
smoke_tests/test6_vad_detector.py
smoke_tests/test7_audio_manager.py
smoke_tests/test8_buffered_player.py
smoke_tests/test9_audio_pipeline.py
voxstream/__init__.py
voxstream/exceptions.py
voxstream/config/__init__.py
voxstream/config/types.py
voxstream/core/__init__.py
voxstream/core/buffer.py
voxstream/core/processor.py
voxstream/core/stream.py
voxstream/interfaces/__init__.py
voxstream/interfaces/base.py
voxstream/io/__init__.py
voxstream/io/capture.py
voxstream/io/manager.py
voxstream/io/player.py
voxstream/utils/__init__.py
voxstream/voice/__init__.py
voxstream/voice/vad.py
voxstream-0.1.0.dist-info/METADATA
voxstream-0.1.0.dist-info/WHEEL
voxstream-0.1.0.dist-info/entry_points.txt
voxstream-0.1.0.dist-info/top_level.txt
voxstream-0.1.0.dist-info/RECORD
